{
  "id": "0015",
  "title": "公众号引流",
  "summary": "用公众号内容引流到私域卖高客单产品，短文吸引流量，长文筛选付费用户，一篇爆文可带来几万到几十万流水。",
  "highlights": "流量成本低｜高客单转化｜长期复利",
  "platform": [
    "微信公众号"
  ],
  "profitModel": "引流",
  "caseRevenue": "案例：一篇4-5万阅读转化120-250精准用户",
  "coverImage": "https://cdn.jsdelivr.net/gh/wu15944567827/-@main/images/%E9%A1%B9%E7%9B%AE15_%E6%A1%88%E4%BE%8B-1.jpg",
  "publishTime": "2025-12-28 09:00",
  "detailContent": {
    "overview": "很多人觉得公众号已经过时了，但你知道吗？**中老年+高净值人群仍然高度依赖公众号**。\n\n茶、酒、滋补品、收藏品，这些高客单商品本来就不在短视频完成转化。用户需要的是信任，而信任需要时间建立。公众号的长文形式，天然适合讲故事、建立信任。\n\n**核心逻辑不是「写公众号赚钱」，而是用强故事+反常识内容把目标用户引到私域**。比如「花50万买假茶」这种亲身踩坑叙事，文末不卖货只给判断，引导加微信私聊。\n\n一篇4-5万阅读的文章，能转化120-250个精准用户。茶叶类目客单几千到几万，5-10单成交就是几万到几十万流水。一天10条图文，好的时候能给私域带来200个流量，单个流量成本极低。",
    "caseImages": [
      {
        "imageUrl": "https://cdn.jsdelivr.net/gh/wu15944567827/-@main/images/%E9%A1%B9%E7%9B%AE15_%E6%A1%88%E4%BE%8B-1.jpg",
        "order": 1,
        "caseTitle": "公众号卖普洱茶",
        "profitDetail": "微信公众号发茶叶故事，几万阅读量引流加微信，卖普洱茶叶，月入数千到上万",
        "type": "中标",
        "publishTime": "2025-12-19 22:43"
      },
      {
        "imageUrl": "https://cdn.jsdelivr.net/gh/wu15944567827/-@main/images/%E9%A1%B9%E7%9B%AE15_%E6%A1%88%E4%BE%8B-2.jpg",
        "order": 2,
        "caseTitle": "500块投出万次阅读",
        "profitDetail": "公众号卖茶叶，找到爆款后追投，月赚3千到1万",
        "type": "中标",
        "publishTime": "2025-12-18 12:32"
      },
      {
        "imageUrl": "https://cdn.jsdelivr.net/gh/wu15944567827/-@main/images/%E9%A1%B9%E7%9B%AE15_%E6%A1%88%E4%BE%8B-3.jpg",
        "order": 3,
        "caseTitle": "小城号外赚流量钱",
        "profitDetail": "做小城市公众号发本地名人事迹，靠广告和同城项目月赚2千到8千",
        "type": "中标",
        "publishTime": "2025-11-11 18:32"
      },
      {
        "imageUrl": "https://cdn.jsdelivr.net/gh/wu15944567827/-@main/images/%E9%A1%B9%E7%9B%AE15_%E6%A1%88%E4%BE%8B-4.jpg",
        "order": 4,
        "caseTitle": "搜软件进公众号",
        "profitDetail": "公众号发软件资源，用户下载拉新，赚1到3块一个，月入3千到1万",
        "type": "中标",
        "publishTime": "2025-11-03 17:25"
      },
      {
        "imageUrl": "https://cdn.jsdelivr.net/gh/wu15944567827/-@main/images/%E9%A1%B9%E7%9B%AE15_%E6%A1%88%E4%BE%8B-5.jpg",
        "order": 5,
        "caseTitle": "公众号引20人加微信",
        "profitDetail": "公众号引流到微信，20个精准客户，卖课程或服务，月赚几千到几万",
        "type": "中标",
        "publishTime": "2025-09-13 12:22"
      }
    ],
    "whyWorthDoing": [
      "**流量成本极低**：一天10条公众号图文，好的时候能给私域带来200个流量，单个获客成本几乎为零",
      "**高客单转化**：茶叶类目客单几千到几万，一篇4-5万阅读文章转化120-250个精准用户，5-10单成交就是几万到几十万流水",
      "**长期复利**：垂直内容可以长期挂在主页持续引流，好内容会被算法持续推荐，不是一次性流量"
    ],
    "howToProfit": [
      "**私域成交**：引导加微信，1v1沟通预算口味，先寄样再成交，高信任促成高客单",
      "**付费投放放大**：小额投放（500元起）撬动系统推荐流量，标题含被推荐过的关键词效果更好",
      "**多元变现**：流量主收益、网盘拉新、地方号同城付费项目等组合变现"
    ],
    "costAndRevenue": {
      "startupCost": "**0-500元**，付费投放可选，从500阅读基础投放起步测试",
      "expectedRevenue": "**一篇4-5万阅读转化120-250精准用户**，茶叶类目客单几千到几万，5-10单成交即几万到几十万流水",
      "paybackPeriod": "**1-4周**，找到被系统推荐的关键词后，爆文即可快速转化"
    },
    "steps": [
      "**写故事型内容**：比如「花50万买假茶」这种亲身踩坑叙事，用强情绪+反常识吸引目标用户",
      "**文末不卖货只给判断**：不放商城不挂链接，只说通过谁解决的，降低防备心",
      "**引导加微信**：评论区垂直互动，私下1v1沟通建立信任",
      "**小额投放测试**：用500元基础投放测试标题关键词，找到被推荐过的词追投放大",
      "**私域成交**：先寄样再成交，高信任+高客单完成转化"
    ],
    "caseReferences": {
      "站内": [
        {
          "order": 1,
          "author": "⃰辰风",
          "authorLink": "https://scys.com/personal/818409?number=59368",
          "publishTime": "2025-12-19 22:43",
          "caseTitle": "公众号卖普洱茶",
          "profitDetail": "微信公众号发茶叶故事，几万阅读量引流加微信，卖普洱茶叶，月入数千到上万",
          "link": "https://scys.com/articleDetail/xq_topic/45811851488842528",
          "type": "中标"
        },
        {
          "order": 2,
          "author": "深元哥",
          "authorLink": "https://scys.com/personal/208795?number=40778",
          "publishTime": "2025-12-18 12:32",
          "caseTitle": "500块投出万次阅读",
          "profitDetail": "公众号卖茶叶，找到爆款后追投，月赚3千到1万",
          "link": "https://scys.com/articleDetail/xq_topic/82811824242451542",
          "type": "中标"
        },
        {
          "order": 3,
          "author": "好运.",
          "authorLink": "https://scys.com/personal/460267?number=36678",
          "publishTime": "2025-11-11 18:32",
          "caseTitle": "小城号外赚流量钱",
          "profitDetail": "做小城市公众号发本地名人事迹，靠广告和同城项目月赚2千到8千",
          "link": "https://scys.com/articleDetail/xq_topic/14588282825515822",
          "type": "中标"
        },
        {
          "order": 4,
          "author": "嘉应岛主",
          "authorLink": "https://scys.com/personal/7535?number=18954",
          "publishTime": "2025-11-03 17:25",
          "caseTitle": "搜软件进公众号",
          "profitDetail": "公众号发软件资源，用户下载拉新，赚1到3块一个，月入3千到1万",
          "link": "https://scys.com/articleDetail/xq_topic/82811544851481482",
          "type": "中标"
        },
        {
          "order": 5,
          "author": "森林",
          "authorLink": "https://scys.com/personal/2758754?number=125007",
          "publishTime": "2025-09-13 12:22",
          "caseTitle": "公众号引20人加微信",
          "profitDetail": "公众号引流到微信，20个精准客户，卖课程或服务，月赚几千到几万",
          "link": "https://scys.com/articleDetail/xq_topic/4842485115222518?_from=%2Fai%2F20260105080141jh5Lx1N",
          "type": "生财好事"
        }
      ],
      "平台": []
    },
    "relatedLinks": {
      "文章": [
        {
          "order": 1,
          "author": "/",
          "authorLink": "",
          "publishTime": "2025-12",
          "title": "垂直小号 - 公众号",
          "link": "https://scys.com/activity/landing/8964?tabIndex=0",
          "type": "航海"
        },
        {
          "order": 2,
          "author": "程弈人",
          "authorLink": "https://scys.com/personal/1142058?number=116953",
          "publishTime": "2025-11-24 12:03",
          "title": "从2024年起，我们在微信生态调整IP获客策略实现高速增长的做法",
          "link": "https://scys.com/articleDetail/xq_topic/55188125482411144",
          "type": "精华"
        },
        {
          "order": 3,
          "author": "东山老师",
          "authorLink": "https://scys.com/personal/209589?number=41338",
          "publishTime": "2025-08-05 22:08",
          "title": "公众号垂直小号变现，窄、专、粘是关键​",
          "link": "https://scys.com/articleDetail/xq_topic/5125858822812224?_from=%2Fai%2F20260105080133qo5qHgp",
          "type": "精华"
        },
        {
          "order": 4,
          "author": "苏晚不晚",
          "authorLink": "https://scys.com/personal/2691026?number=125542",
          "publishTime": "2025-10-16 23:06",
          "title": "如何用垂直小号高效引流私域，设置文章钩子，快速获客400+",
          "link": "https://scys.com/articleDetail/xq_topic/14588258158244152",
          "type": "帖子"
        },
        {
          "order": 5,
          "author": "领飞懂运营",
          "authorLink": "https://scys.com/personal/206046?number=24560",
          "publishTime": "2025-07-18 17:15",
          "title": "宝妈【在家事业】从卖资料开始，成为年入50万的“教培”中介女王",
          "link": "https://scys.com/articleDetail/xq_topic/1524855581454552?_from=%2Fai%2F20260105080133qo5qHgp",
          "type": "帖子"
        }
      ],
      "政策": []
    }
  },
  "statistics": {
    "clickCount": 732,
    "readCount": 610,
    "favoriteCount": 9,
    "likeCount": 31,
    "commentCount": 3,
    "shareCount": 1
  }
}